pymatchit-0.1.0.dist-info/METADATA
pymatchit-0.1.0.dist-info/WHEEL
pymatchit-0.1.0.dist-info/licenses/LICENSE
pymatchit/__init__.py
pymatchit/py.typed
pymatchit/pymatchit.cpython-310-x86_64-linux-gnu.so
pymatchit/pymatchit.pyi
pymatchit-0.1.0.dist-info/RECORD
