Metadata-Version: 2.4
Name: pymatchit
Version: 0.1.0
Classifier: Development Status :: 4 - Beta
Classifier: Programming Language :: Rust
Classifier: Programming Language :: Python :: Implementation :: CPython
Classifier: Programming Language :: Python :: Implementation :: PyPy
Classifier: Programming Language :: Python
Requires-Dist: pytest ; extra == 'tests'
Provides-Extra: tests
License-File: LICENSE
Summary: Python bindings for the `matchit` URL router
Author: Aprila Hijriyan <april@kuli.dev>
Author-email: Aprila Hijriyan <april@kuli.dev>
License: MIT OR BSD-3-Clause
Requires-Python: >=3.9
Project-URL: homepage, https://github.com/aprilahijriyan/pymatchit
Project-URL: documentation, https://github.com/aprilahijriyan/pymatchit
Project-URL: repository, https://github.com/aprilahijriyan/pymatchit
